arti/__init__.py
arti/annotations/__init__.py
arti/artifacts/__init__.py
arti/backends/__init__.py
arti/backends/memory.py
arti/executors/__init__.py
arti/executors/local.py
arti/fingerprints/__init__.py
arti/formats/__init__.py
arti/formats/json.py
arti/formats/pickle.py
arti/graphs/__init__.py
arti/internal/__init__.py
arti/internal/dispatch.py
arti/internal/models.py
arti/internal/patches.py
arti/internal/type_hints.py
arti/internal/utils.py
arti/internal/vendored/setuptools.py
arti/io/__init__.py
arti/io/json_gcsfile_python.py
arti/io/json_localfile_python.py
arti/io/json_stringliteral_python.py
arti/io/pickle_gcsfile_python.py
arti/io/pickle_localfile_python.py
arti/partitions/__init__.py
arti/producers/__init__.py
arti/py.typed
arti/statistics/__init__.py
arti/storage/__init__.py
arti/storage/_internal.py
arti/storage/google/cloud/storage.py
arti/storage/literal.py
arti/storage/local.py
arti/thresholds/__init__.py
arti/types/__init__.py
arti/types/bigquery.py
arti/types/numpy.py
arti/types/pandas.py
arti/types/pyarrow.py
arti/types/pydantic.py
arti/types/python.py
arti/versions/__init__.py
arti/views/__init__.py
arti/views/python.py
arti-0.0.4.dist-info/LICENSE
arti-0.0.4.dist-info/METADATA
arti-0.0.4.dist-info/WHEEL
arti-0.0.4.dist-info/RECORD
