Metadata-Version: 2.1
Name: arti
Version: 0.0.4
Summary: 
Home-page: https://github.com/artigraph/artigraph
License: Apache-2.0
Author: Jacob Hayes
Author-email: jacob.r.hayes@gmail.com
Requires-Python: >=3.9,<4.0
Classifier: License :: OSI Approved :: Apache Software License
Classifier: Programming Language :: Python :: 3
Classifier: Programming Language :: Python :: 3.9
Classifier: Programming Language :: Python :: 3.10
Classifier: Programming Language :: Python :: 3.11
Provides-Extra: all
Requires-Dist: gcsfs (>=2022.2.0) ; extra == "all"
Requires-Dist: google-cloud-bigquery (>=3.5.0,<4.0.0) ; extra == "all"
Requires-Dist: multimethod (>=1.6)
Requires-Dist: numpy (>=1.23.1) ; extra == "all"
Requires-Dist: pandas (>=1.4.3) ; extra == "all"
Requires-Dist: parse (>=1.19.0)
Requires-Dist: pyarrow (>=8) ; extra == "all"
Requires-Dist: pydantic (>=1.9.0,<2)
Requires-Dist: pyfarmhash (>=0.2.2)
Requires-Dist: python-box (>=7.0.0)
Project-URL: Repository, https://github.com/artigraph/artigraph
